d2_nip_eval/NTIPAliasClass.py
d2_nip_eval/NTIPAliasClassID.py
d2_nip_eval/NTIPAliasFlag.py
d2_nip_eval/NTIPAliasQuality.py
d2_nip_eval/NTIPAliasStat.py
d2_nip_eval/NTIPAliasType.py
d2_nip_eval/__init__.py
d2_nip_eval/lexer.py
d2_nip_eval/tokens.py
d2_nip_eval-0.0.1.dist-info/METADATA
d2_nip_eval-0.0.1.dist-info/WHEEL
d2_nip_eval-0.0.1.dist-info/top_level.txt
d2_nip_eval-0.0.1.dist-info/RECORD
