Metadata-Version: 2.1
Name: d2-nip-eval
Version: 0.0.1
Summary: D2 nip-eval is a package aimed to help in providing an API for converting nip expressions into python eval statements
Home-page: https://github.com/Ezro/d2_nip_to_eval
License: UNKNOWN
Platform: UNKNOWN
Classifier: Programming Language :: Python :: 3
Classifier: License :: OSI Approved :: MIT License
Classifier: Operating System :: Microsoft :: Windows :: Windows 10
